hypermindz_tools/__init__.py
hypermindz_tools/crewai/__init__.py
hypermindz_tools/crewai/rag_search.py
hypermindz_tools-0.1.0.dist-info/licenses/LICENSE
hypermindz_tools-0.1.0.dist-info/METADATA
hypermindz_tools-0.1.0.dist-info/WHEEL
hypermindz_tools-0.1.0.dist-info/top_level.txt
hypermindz_tools-0.1.0.dist-info/RECORD
