Metadata-Version: 2.4
Name: hypermindz-tools
Version: 0.1.0
Summary: A collection of tools for Hypermindz AI workflows, including CrewAI integrations
Home-page: https://github.com/yourusername/hypermindz-tools
Author: Hypermindz Team
Author-email: Your Name <your.email@example.com>
License: MIT
Project-URL: Homepage, https://github.com/yourusername/hypermindz-tools
Project-URL: Documentation, https://github.com/yourusername/hypermindz-tools#readme
Project-URL: Repository, https://github.com/yourusername/hypermindz-tools
Project-URL: Bug Tracker, https://github.com/yourusername/hypermindz-tools/issues
Keywords: ai,crewai,rag,search,hypermindz
Classifier: Development Status :: 3 - Alpha
Classifier: Intended Audience :: Developers
Classifier: License :: OSI Approved :: MIT License
Classifier: Operating System :: OS Independent
Classifier: Programming Language :: Python :: 3
Classifier: Programming Language :: Python :: 3.10
Classifier: Programming Language :: Python :: 3.11
Classifier: Programming Language :: Python :: 3.12
Classifier: Topic :: Software Development :: Libraries :: Python Modules
Classifier: Topic :: Scientific/Engineering :: Artificial Intelligence
Requires-Python: >=3.8
License-File: LICENSE
Requires-Dist: requests>=2.25.0
Requires-Dist: crewai>=0.76.2
Provides-Extra: dev
Requires-Dist: pytest>=6.0; extra == "dev"
Requires-Dist: pytest-cov>=2.10.0; extra == "dev"
Requires-Dist: black>=21.0.0; extra == "dev"
Requires-Dist: flake8>=3.9.0; extra == "dev"
Requires-Dist: mypy>=0.910; extra == "dev"
Requires-Dist: twine>=3.4.0; extra == "dev"
Requires-Dist: build>=0.7.0; extra == "dev"
Dynamic: author
Dynamic: home-page
Dynamic: license-file
Dynamic: requires-python
